fuzzylinguistics/__init__.py
fuzzylinguistics/_version.py
fuzzylinguistics/fls_pydantic_interface.py
fuzzylinguistics/fuzzy_linguistic_summaries.py
fuzzylinguistics-0.2.1.dist-info/licenses/LICENSE
fuzzylinguistics-0.2.1.dist-info/METADATA
fuzzylinguistics-0.2.1.dist-info/WHEEL
fuzzylinguistics-0.2.1.dist-info/top_level.txt
fuzzylinguistics-0.2.1.dist-info/RECORD
