Metadata-Version: 2.4
Name: fuzzylinguistics
Version: 0.2.1
Summary: A Python library for generating and simplifying fuzzy linguistic summaries of data.
Author-email: Brendan Alvey <lyvelyte@gmail.com>
License:                                  Apache License
Project-URL: Homepage, https://github.com/lyvelyte/fuzzylinguistics
Project-URL: Bug Tracker, https://github.com/lyvelyte/fuzzylinguistics/issues
Project-URL: Repository, https://github.com/lyvelyte/fuzzylinguistics
Keywords: fuzzy logic,linguistic summary,explainable AI,XAI,natural language generation,data science
Classifier: Development Status :: 3 - Alpha
Classifier: Intended Audience :: Developers
Classifier: Intended Audience :: Science/Research
Classifier: License :: OSI Approved :: Apache Software License
Classifier: Operating System :: OS Independent
Classifier: Programming Language :: Python :: 3
Classifier: Programming Language :: Python :: 3.8
Classifier: Programming Language :: Python :: 3.9
Classifier: Programming Language :: Python :: 3.10
Classifier: Programming Language :: Python :: 3.11
Classifier: Programming Language :: Python :: 3.12
Classifier: Topic :: Scientific/Engineering :: Information Analysis
Classifier: Topic :: Text Processing :: Linguistic
Requires-Python: >=3.8
License-File: LICENSE
Requires-Dist: numpy
Requires-Dist: pydantic
Requires-Dist: pydantic-numpy
Requires-Dist: networkx
Requires-Dist: matplotlib
Requires-Dist: tqdm
Requires-Dist: pandas
Dynamic: license-file
